CHANGES.rst
LICENSE.txt
MANIFEST.in
README.rst
setup.py
actrack/__init__.py
actrack/actions.py
actrack/actions_queue.py
actrack/apps.py
actrack/compat.py
actrack/decorators.py
actrack/deletion.py
actrack/descriptors.py
actrack/fields.py
actrack/gfk.py
actrack/handler.py
actrack/helpers.py
actrack/level.py
actrack/models.py
actrack/settings.py
actrack/signals.py
actrack/version.py
actrack/managers/__init__.py
actrack/managers/default.py
actrack/managers/inst.py
actrack/migrations/0001_initial.py
actrack/migrations/0002_alter_action_fields.py
actrack/migrations/__init__.py
django_actrack.egg-info/PKG-INFO
django_actrack.egg-info/SOURCES.txt
django_actrack.egg-info/dependency_links.txt
django_actrack.egg-info/requires.txt
django_actrack.egg-info/top_level.txt