Metadata-Version: 1.1
Name: django-actrack
Version: 1.0
Summary: An activity tracker for Django
Home-page: https://github.com/tkhyn/django-actrack
Author: Thomas Khyn
Author-email: thomas@ksytek.com
License: UNKNOWN
Platform: UNKNOWN
Classifier: Programming Language :: Python
Classifier: Programming Language :: Python :: 3
Classifier: License :: OSI Approved :: MIT License
Classifier: Operating System :: OS Independent
Classifier: Development Status :: 5 - Production/Stable
Classifier: Framework :: Django
Classifier: Environment :: Other Environment
Classifier: Intended Audience :: Developers
Classifier: Topic :: Software Development
